{
  "hero": {
    "src": "/static/image/staticPages/valve_index.jpg",
    "head": "Valve Index"
  },
  "services": {
    "base": [
      {
        "page": "valve-index",
        "service": "Valve index",
        "id": "1111AM-VI",
        "background": "/static/image/services/valve/valve_index_min.jpg",
        "description": {
          "text": "אינדקס Valve הן משקפי מציאות מדומה שמיוצרת על ידי Valve Corporation.המשקפיים משתמשות בפאנל LCD 1440 × 1600 לכל עין ברזולוציה משולבת של 2880 × 1600.העדשות הן RGB מלאות ויכולים לפעול בקצבי רענון של 80 הרץ, 90 הרץ, 120 הרץ, או במצב ניסוי כרגע של 144 הרץ.המשקפיים משתמשות בגרסה משופרת של מערכת המעקב אחר המגדלור של Valve.המשקפיים מיועדות לשימוש עם בקרי אינדקס, הידועים במהלך הפיתוח כבקרי קנקלס, אך הם גם תואמים לאחור עם בקרי HTC Vive ו- HTC Vive Pro.אינדקס Valve תומך הן במערכות ההפעלה Windows והן ב- Linux.",
          "detailes": {
            "manufacture": "Valve",
            "mfctrUrl": "https://www.valvesoftware.com/en/index",
            "supplyTime": 7,
            "warranty": 1,
            "price": 8599
          }
        },
        "img": [
          { "src": "/static/image/services/valve/plays.jpg" },
          { "src": "/static/image/services/valve/plays_2.jpg" },
          { "src": "/static/image/services/valve/plays_3.jpg" },
          { "src": "/static/image/services/valve/plays_4.jpg" }
        ],
        "warrning": "דרוש מחשב תומך"
      }
    ]
  },
  "manufactureData": [
    {
      "text": "חברת Valve Corporation היא מפתחת, מפרסמת וחברת הפצה דיגיטלית אמריקאית, הם אלו שפיתחו את פלטפורמת Steam ומשחקי Half-Life, Counter-Strike, Portal, Day of Defeat, Fortress Team, Left 4 Dead ו- Dota 2. "
    },
    {
      "text": "במרץ 2015 הודיעו Valve וחברת האלקטרוניקה הטייוואנית HTC על פרויקט משותף לפיתוח ה- HTC Vive, משקפי מציאות מדומה עם בקרי מעקב אחר תנועה. החברות עובדות עם גוגל, ליונס גייט ו- HBO לפיתוח תוכן למכשיר."
    },
    {
      "text": "לאחר שחרורו של ה- Vive, Valve החלה בפיתוח חומרת VR משלהם."
    },
    {
      "text": "מערכת ה- VR של Valve משקפיים שיכולות לפעול בקצב פריים של עד 144 ברזולוציה של 1440 × 1600 לכל עין, זוג בקרי כף יד של SteamVR Knuckles שכל אחד מהם מעל 80 חיישנים שונים לפיקוח על תנועת היד, וזוג תחנות בסיס כדי לעקוב אחר תנועותיו של השחקן."
    },
    {
      "text": " המערכת כוללת תאימות לאחור למשחקי HTC Vive."
    }
  ]
}
